Core001/multiple.py
EulerOS-1.0.0.dist-info/DESCRIPTION.rst
EulerOS-1.0.0.dist-info/METADATA
EulerOS-1.0.0.dist-info/RECORD
EulerOS-1.0.0.dist-info/WHEEL
EulerOS-1.0.0.dist-info/metadata.json
EulerOS-1.0.0.dist-info/top_level.txt
