Metadata-Version: 2.0
Name: EulerOS
Version: 1.0.0
Summary: Euler Math Thinking: Small Dog Edition
Home-page: UNKNOWN
Author: Small Dog
Author-email: UNKNOWN
License: Small Dog Inc., UCB
Platform: UNKNOWN
Classifier: Programming Language :: Python :: 3
Classifier: Programming Language :: Python :: 3.6
